env/__init__.py
env/cli.py
autoPyEnV-0.1.0.dist-info/METADATA
autoPyEnV-0.1.0.dist-info/WHEEL
autoPyEnV-0.1.0.dist-info/entry_points.txt
autoPyEnV-0.1.0.dist-info/top_level.txt
autoPyEnV-0.1.0.dist-info/RECORD
