Metadata-Version: 2.2
Name: autoPyEnV
Version: 0.1.0
Summary: An automated Python environment management tool
Home-page: https://github.com/WolvarineXD/autoPyEnV
Author: Your Name
Classifier: Programming Language :: Python :: 3
Classifier: License :: OSI Approved :: MIT License
Classifier: Operating System :: OS Independent
Requires-Python: >=3.6
Requires-Dist: click
Dynamic: author
Dynamic: classifier
Dynamic: home-page
Dynamic: requires-dist
Dynamic: requires-python
Dynamic: summary
